{
   "CodeGenerationMode": 5,
   "ContextClassName": "db37500Context",
   "ContextNamespace": null,
   "FilterSchemas": false,
   "IncludeConnectionString": true,
   "IrregularWords": null,
   "MinimumProductVersion": "2.6.1301",
   "ModelNamespace": null,
   "OutputContextPath": null,
   "OutputPath": "Models",
   "PluralRules": null,
   "PreserveCasingWithRegex": true,
   "ProjectRootNamespace": "Examination_system",
   "Schemas": null,
   "SelectedHandlebarsLanguage": 2,
   "SelectedToBeGenerated": 0,
   "SingularRules": null,
   "T4TemplatePath": null,
   "Tables": [
      {
         "Name": "[dbo].[branch]",
         "ObjectType": 0
      },
      {
         "Name": "[dbo].[branch_department]",
         "ObjectType": 0
      },
      {
         "Name": "[dbo].[course_questions_on_topic]",
         "ObjectType": 0
      },
      {
         "Name": "[dbo].[courses]",
         "ObjectType": 0
      },
      {
         "Name": "[dbo].[department]",
         "ObjectType": 0
      },
      {
         "Name": "[dbo].[department_courses]",
         "ObjectType": 0
      },
      {
         "Name": "[dbo].[exam]",
         "ObjectType": 0
      },
      {
         "Name": "[dbo].[exam_questions]",
         "ObjectType": 0
      },
      {
         "Name": "[dbo].[instructor]",
         "ObjectType": 0
      },
      {
         "Name": "[dbo].[instructor_course]",
         "ObjectType": 0
      },
      {
         "Name": "[dbo].[instructor_generate_course_exam]",
         "ObjectType": 0
      },
      {
         "Name": "[dbo].[person]",
         "ObjectType": 0
      },
      {
         "Name": "[dbo].[person_jong_department_branch]",
         "ObjectType": 0
      },
      {
         "Name": "[dbo].[quesiton_choice]",
         "ObjectType": 0
      },
      {
         "Name": "[dbo].[question]",
         "ObjectType": 0
      },
      {
         "Name": "[dbo].[question_choise_bridge]",
         "ObjectType": 0
      },
      {
         "Name": "[dbo].[student]",
         "ObjectType": 0
      },
      {
         "Name": "[dbo].[student_answer_question]",
         "ObjectType": 0
      },
      {
         "Name": "[dbo].[student_course]",
         "ObjectType": 0
      },
      {
         "Name": "[dbo].[student_exam]",
         "ObjectType": 0
      },
      {
         "Name": "[dbo].[topic]",
         "ObjectType": 0
      },
      {
         "Name": "[dbo].[AddBranch]",
         "ObjectType": 1
      },
      {
         "Name": "[dbo].[AddCourse]",
         "ObjectType": 1
      },
      {
         "Name": "[dbo].[AddCourseToDepartment]",
         "ObjectType": 1
      },
      {
         "Name": "[dbo].[AddDepartment]",
         "ObjectType": 1
      },
      {
         "Name": "[dbo].[AddDepartmentToBranch]",
         "ObjectType": 1
      },
      {
         "Name": "[dbo].[AddInstructor]",
         "ObjectType": 1
      },
      {
         "Name": "[dbo].[AddStudent]",
         "ObjectType": 1
      },
      {
         "Name": "[dbo].[AddTopic]",
         "ObjectType": 1
      },
      {
         "Name": "[dbo].[AssignInstructorToCourse]",
         "ObjectType": 1
      },
      {
         "Name": "[dbo].[CorrectExam]",
         "ObjectType": 1
      },
      {
         "Name": "[dbo].[DeleteBranch]",
         "ObjectType": 1
      },
      {
         "Name": "[dbo].[DeleteChoice]",
         "ObjectType": 1
      },
      {
         "Name": "[dbo].[DeleteCourse]",
         "ObjectType": 1
      },
      {
         "Name": "[dbo].[DeleteDepartment]",
         "ObjectType": 1
      },
      {
         "Name": "[dbo].[DeleteExam]",
         "ObjectType": 1
      },
      {
         "Name": "[dbo].[DeleteInstructor]",
         "ObjectType": 1
      },
      {
         "Name": "[dbo].[DeleteQuestion]",
         "ObjectType": 1
      },
      {
         "Name": "[dbo].[DeleteStudent]",
         "ObjectType": 1
      },
      {
         "Name": "[dbo].[DeleteTopic]",
         "ObjectType": 1
      },
      {
         "Name": "[dbo].[EnrollStudentInCourse]",
         "ObjectType": 1
      },
      {
         "Name": "[dbo].[GenerateExam]",
         "ObjectType": 1
      },
      {
         "Name": "[dbo].[GetAllExams]",
         "ObjectType": 1
      },
      {
         "Name": "[dbo].[GetAllInstructors]",
         "ObjectType": 1
      },
      {
         "Name": "[dbo].[GetAllQuestionsWithChoicesPivoted]",
         "ObjectType": 1
      },
      {
         "Name": "[dbo].[GetAllStudents]",
         "ObjectType": 1
      },
      {
         "Name": "[dbo].[GetBranchById]",
         "ObjectType": 1
      },
      {
         "Name": "[dbo].[GetChoicesByQuestionId]",
         "ObjectType": 1
      },
      {
         "Name": "[dbo].[GetCourseById]",
         "ObjectType": 1
      },
      {
         "Name": "[dbo].[GetCourseTopics]",
         "ObjectType": 1
      },
      {
         "Name": "[dbo].[GetDepartmentById]",
         "ObjectType": 1
      },
      {
         "Name": "[dbo].[GetDepartmentCourses]",
         "ObjectType": 1
      },
      {
         "Name": "[dbo].[GetExamById]",
         "ObjectType": 1
      },
      {
         "Name": "[dbo].[GetExamQuestions]",
         "ObjectType": 1
      },
      {
         "Name": "[dbo].[GetExamQuestionsWithChoicesPivoted]",
         "ObjectType": 1
      },
      {
         "Name": "[dbo].[GetInstructorById]",
         "ObjectType": 1
      },
      {
         "Name": "[dbo].[GetInstructorCourses]",
         "ObjectType": 1
      },
      {
         "Name": "[dbo].[GetQuestionsForCourseTopic]",
         "ObjectType": 1
      },
      {
         "Name": "[dbo].[GetQuestionWithChoices]",
         "ObjectType": 1
      },
      {
         "Name": "[dbo].[GetQuestionWithChoicesPivoted]",
         "ObjectType": 1
      },
      {
         "Name": "[dbo].[GetStudentById]",
         "ObjectType": 1
      },
      {
         "Name": "[dbo].[GetStudentCourses]",
         "ObjectType": 1
      },
      {
         "Name": "[dbo].[GetTopicById]",
         "ObjectType": 1
      },
      {
         "Name": "[dbo].[InsertMCQChoice]",
         "ObjectType": 1
      },
      {
         "Name": "[dbo].[InsertQuestion]",
         "ObjectType": 1
      },
      {
         "Name": "[dbo].[InsertTrueFalseChoices]",
         "ObjectType": 1
      },
      {
         "Name": "[dbo].[LinkQuestionToCourseTopic]",
         "ObjectType": 1
      },
      {
         "Name": "[dbo].[RemoveCourseFromDepartment]",
         "ObjectType": 1
      },
      {
         "Name": "[dbo].[RemoveInstructorFromCourse]",
         "ObjectType": 1
      },
      {
         "Name": "[dbo].[sp_GetExamForStudent]",
         "ObjectType": 1
      },
      {
         "Name": "[dbo].[StudentSubmitAnswers]",
         "ObjectType": 1
      },
      {
         "Name": "[dbo].[UnenrollStudentFromCourse]",
         "ObjectType": 1
      },
      {
         "Name": "[dbo].[UnlinkQuestionFromCourseTopic]",
         "ObjectType": 1
      },
      {
         "Name": "[dbo].[UpdateBranch]",
         "ObjectType": 1
      },
      {
         "Name": "[dbo].[UpdateChoiceText]",
         "ObjectType": 1
      },
      {
         "Name": "[dbo].[UpdateCourse]",
         "ObjectType": 1
      },
      {
         "Name": "[dbo].[UpdateDepartment]",
         "ObjectType": 1
      },
      {
         "Name": "[dbo].[UpdateExam]",
         "ObjectType": 1
      },
      {
         "Name": "[dbo].[UpdateInstructor]",
         "ObjectType": 1
      },
      {
         "Name": "[dbo].[UpdateQuestion]",
         "ObjectType": 1
      },
      {
         "Name": "[dbo].[UpdateQuestionCorrectAnswer]",
         "ObjectType": 1
      },
      {
         "Name": "[dbo].[UpdateStudent]",
         "ObjectType": 1
      },
      {
         "Name": "[dbo].[UpdateTopic]",
         "ObjectType": 1
      }
   ],
   "UiHint": null,
   "UncountableWords": null,
   "UseAsyncStoredProcedureCalls": true,
   "UseBoolPropertiesWithoutDefaultSql": false,
   "UseDatabaseNames": true,
   "UseDatabaseNamesForRoutines": true,
   "UseDateOnlyTimeOnly": true,
   "UseDbContextSplitting": false,
   "UseDecimalDataAnnotationForSprocResult": true,
   "UseFluentApiOnly": false,
   "UseHandleBars": false,
   "UseHierarchyId": false,
   "UseInflector": true,
   "UseInternalAccessModifiersForSprocsAndFunctions": false,
   "UseLegacyPluralizer": false,
   "UseManyToManyEntity": false,
   "UseNoDefaultConstructor": false,
   "UseNoNavigations": false,
   "UseNoObjectFilter": false,
   "UseNodaTime": false,
   "UseNullableReferences": false,
   "UsePrefixNavigationNaming": false,
   "UseSchemaFolders": false,
   "UseSchemaNamespaces": false,
   "UseSpatial": false,
   "UseT4": false,
   "UseT4Split": false
}